Workbook

Sheet README
A1: PERSONAL FINANCIAL FREEDOM PLANNER
A3: PROJECT OBJECTIVE
A4: BUILD AN EXCEL-BASED TOOL THAT ANALYZES INCOME, EXPENSES, SAVINGS, INVESTMENTS, AND NET WORTH, AND USES SCENARIO ANALYSIS TO ESTIMATE THE PATH TOWARD FINANCIAL FREEDOM.
A6: PROBLEM STATEMENT
A7: PEOPLE OFTEN HAVE FINANCIAL DATA BUT LACK A SIMPLE WAY TO UNDERSTAND THEIR SPENDING, PATTERNS, SAVING BEHAVIOUR, WEALTH GROWTH, AND LONG TERM FINANCIAL TRAJECTORY
A9: CORE FEATURES
A10: 1. INCOME AND EXPENSE TRACKING
A11: 2. MONTHLY FINANCIAL ANALYSIS
A12: 3. NET WORTH TRACKING
A13: 4. INVESTMENT GROWTH PROJECTIONS
A14: 5. SCENARIO ANALYSIS
A15: 6. FINANCIAL DASHBOARD
... A23: VERSION 0.1 — BUILDING THE FOUNDATION

Sheet Inputs
A1: FINANCIAL FREEDOM PLANNER — USER INPUTS
A3: PERSONAL INFORMATION
A4: CURRENT AGE | B4: 20
A5: TARGET FINANCIAL FREEDOM AGE | B5: 45
A6: CURRENT MONTHLY INCOME | B6: 60000
A7: EXPECTED ANNUAL INCOME GROWTH | B7: 0.07
A9: CURRENT FINANCIAL POSITION
A10: CURRENT CASH / BANK BALANCE | B10: 200000
A11: CURRENT INVESTMENTS | B11: 100000
A12: CURRENT DEBT / LOANS | B12: 0
A14: MONTHLY FINANCIAL ASSUMPTIONS
A15: EXPECTED MONTHLY EXPENSES | B15: 35000
A16: MONTHLY INVESTMENT CONTRIBUTION | B16: 15000
A17: EXPECTED ANNUAL INVESTMENT RETURN | B17: 0.1
A18: EXPECTED ANNUAL INFLATION RATE | B18: 0.05
A20: FINANCIAL FREEDOM GOAL
A21: TARGET ANNUAL EXPENSES AFTER FINANCIAL FREEDOM | B21: 600000
A22: ASSUMED WITHDRAWAL RATE (4% RULE) | B22: 0.04
A24: 4% RULE NOTE
A25: THE 4% RULE IS A SIMPLIFIED RETIREMENT PLANNING ASSUMPTION THAT ESTIMATES THE PORTFOLIO REQUIRED BY DIVIDING ANNUAL EXPENSES BY A 4% INITIAL WITHDRAWAL RATE. IT IS NOT A GUARANTEE OF SUSTAINABLE INCOME OR FUTURE INVESTMENT PERFORMANCE.

Sheet Transactions
A1: DATE | B1: DESCRIPTION | C1: CATEGORY | D1: TYPE | E1: AMOUNT
A2: 46023 | B2: MONTHLY SALARY | C2: SALARY | D2: INCOME | E2: 60000
A3: 46024 | B3: HOUSE RENT | C3: HOUSING | D3: EXPENSE | E3: 15000
A4: 46026 | B4: GROCERIES | C4: FOOD | D4: EXPENSE | E4: 4500
A5: 46029 | B5: METRO & BUS | C5: TRANSPORT | D5: EXPENSE | E5: 1500
A6: 46032 | B6: SIP INVESTMENT | C6: INVESTMENT | D6: INVESTMENT | E6: 15000
A7: 46037 | B7: ELECTRICITY BILL | C7: UTILITIES | D7: EXPENSE | E7: 1800
A8: 46040 | B8: RESTAURANT | C8: ENTERTAINMENT | D8: EXPENSE | E8: 2000
A9: 46044 | B9: CLOTHING | C9: SHOPPING | D9: EXPENSE | E9: 2500
A10: 46050 | B10: ONLINE SUBSCRIPTION | C10: ENTERTAINMENT | D10: EXPENSE | E10: 500

Sheet Monthly Analysis
A1: JANUARY 2026 FINANCIAL ANALYSIS
A3: METRIC | B3: AMOUNT
A4: TOTAL INCOME | B4: =SUMIF(Transactions!D2:D10,"INCOME",Transactions!E2:E10) -> 60000
A5: TOTAL EXPENSES | B5: =SUMIF(Transactions!D2:D10,"EXPENSE",Transactions!E2:E10) -> 27800
A6: TOTAL INVESTMENTS | B6: =SUMIF(Transactions!D2:D10,"INVESTMENT",Transactions!E2:E10) -> 15000
A7: TOTAL SAVINGS | B7: =B4-B5 -> 32200
A8: SAVINGS RATE | B8: =B7/B4 -> 0.53666667
A10: KEY OBSERVATIONS
A11: INCOME AFTER EXPENSES | B11: 32200
A12: INVESTMENT AS % OF INCOME | B12: =B6/B4 -> 0.25
A13: EXPENSES AS % OF INCOME | B13: =B5/B4 -> 0.46333333

Sheet Net Worth
A1: JANUARY 2026 NET WORTH
A3: ASSETS
A4: CASH / BANK BALANCE | B4: =Inputs!B10 -> 200000
A5: INVESTMENTS | B5: =Inputs!B11 -> 100000
A6: TOTAL ASSETS | B6: =B4+B5 -> 300000
A8: LIABILITIES
A9: DEBT / LOANS | B9: =Inputs!B12 -> 0
A10: TOTAL LIABILITIES | B10: =B9 -> 0
A12: NET WORTH | B12: =B6-B10 -> 300000

Sheet Investment Projection
A1: INVESTMENT GROWTH PROJECTION
A3: INPUT | B3: VALUE
A4: CURRENT INVESTMENTS | B4: =Inputs!B11 -> 100000
A5: MONTHLY INVESTMENT CONTRIBUTION | B5: =Inputs!B16 -> 15000
A6: EXPECTED ANNUAL RETURN | B6: =Inputs!B17 -> 0.1
A7: CURRENT AGE | B7: =Inputs!B4 -> 20
A8: TARGET FINANCIAL FREEDOM AGE | B8: =Inputs!B5 -> 45
A9: INVESTMENT PERIOD ( YEARS ) | B9: =B8-B7 -> 25
A12: YEAR | B12: AGE | C12: ANNUAL INVESTMENT | D12: PROJECTED PORTFOLIO VALUE
A13: 0 | B13: 20 | D13: 100000
A14: =A13+1 -> 1 | B14: =B13+1 -> 21 | C14: =$B$5*12 -> 180000 | D14: =D13*(1+$B$6)+C14 -> 290000
A15: =A14+1 -> 2 | B15: =B14+1 -> 22 | C15: =$B$5*12 -> 180000 | D15: =D14*(1+$B$6)+C15 -> 499000
A16: =A15+1 -> 3 | B16: =B15+1 -> 23 | C16: =$B$5*12 -> 180000 | D16: =D15*(1+$B$6)+C16 -> 728900
A17: =A16+1 -> 4 | B17: =B16+1 -> 24 | C17: =$B$5*12 -> 180000 | D17: =D16*(1+$B$6)+C17 -> 981790
A18: =A17+1 -> 5 | B18: =B17+1 -> 25 | C18: =$B$5*12 -> 180000 | D18: =D17*(1+$B$6)+C18 -> 1259969
A19: =A18+1 -> 6 | B19: =B18+1 -> 26 | C19: =$B$5*12 -> 180000 | D19: =D18*(1+$B$6)+C19 -> 1565965.9
A20: =A19+1 -> 7 | B20: =B19+1 -> 27 | C20: =$B$5*12 -> 180000 | D20: =D19*(1+$B$6)+C20 -> 1902562.5
A21: =A20+1 -> 8 | B21: =B20+1 -> 28 | C21: =$B$5*12 -> 180000 | D21: =D20*(1+$B$6)+C21 -> 2272818.7
A22: =A21+1 -> 9 | B22: =B21+1 -> 29 | C22: =$B$5*12 -> 180000 | D22: =D21*(1+$B$6)+C22 -> 2680100.6
A23: =A22+1 -> 10 | B23: =B22+1 -> 30 | C23: =$B$5*12 -> 180000 | D23: =D22*(1+$B$6)+C23 -> 3128110.7
A24: =A23+1 -> 11 | B24: =B23+1 -> 31 | C24: =$B$5*12 -> 180000 | D24: =D23*(1+$B$6)+C24 -> 3620921.7
A25: =A24+1 -> 12 | B25: =B24+1 -> 32 | C25: =$B$5*12 -> 180000 | D25: =D24*(1+$B$6)+C25 -> 4163013.9
... A38: =A37+1 -> 25 | B38: =B37+1 -> 45 | C38: =$B$5*12 -> 180000 | D38: =D37*(1+$B$6)+C38 -> 18785941
A41: SCENARIO ANALYSIS | B41: ANNUAL RETURN | C41: PROJECTED VALUE AT AGE 45
A44: CONSERVATIVE | B44: 0.08 | C44: =FV(B44,$B$9,-$B$5*12,-$B$4) -> 13843917
A45: BASE | B45: 0.1 | C45: =FV(B45,$B$9,-$B$5*12,-$B$4) -> 18785941
A46: OPTIMISTIC | B46: 0.12 | C46: =FV(B46,$B$9,-$B$5*12,-$B$4) -> 25700103

Sheet Dashboard
A1: PERSONAL FINANCIAL FREEDOM DASHBOARD
A3: CURRENT FINANCIAL SNAPSHOT
A4: MONTHLY INCOME | B4: =Inputs!B6 -> 60000
A5: MONTHLY EXPENSES | B5: ='Monthly Analysis'!B5 -> 27800
A6: MONTHLY SAVINGS | B6: ='Monthly Analysis'!B7 -> 32200
A7: SAVINGS RATE | B7: ='Monthly Analysis'!B8 -> 0.53666667
A8: CURRENT NET WORTH | B8: ='Net Worth'!B12 -> 300000
A10: FINANCIAL FREEDOM PROJECTION
A11: TARGET AGE | B11: =Inputs!B5 -> 45
A12: INVESTMENT PERIOD | B12: ='Investment Projection'!B9 -> 25
A13: PROJECTED VALUE AT TARGET AGE | B13: ='Investment Projection'!C45 -> 18785941
A14: SCENARIO ANALYSIS
A15: CONSERVATIVE (8%) | B15: ='Investment Projection'!C44 -> 13843917
A16: BASE ( 10% ) | B16: ='Investment Projection'!C45 -> 18785941
A17: OPTIMISTIC ( 12% ) | B17: ='Investment Projection'!C46 -> 25700103
A20: FINANCIAL FREEDOM TARGET
A21: TARGET ANNUAL EXPENSE | B21: =Inputs!B21 -> 600000
A22: ASSUMED WITHDRAWAL RATE (4%) | B22: =Inputs!B22 -> 0.04
A23: TARGET PORTFOLIO REQUIRED | B23: =B21/B22 -> 15000000
A24: PROJECTED PORTFOLIO | B24: =B13 -> 18785941
A25: FUNDING GAP/SURPLUS | B25: =B24-B23 -> 3785941.3
A26: FINANCIAL FREEDOM STATUS | B26: =IF(B25>=0,"ON TRACK","BELOW TARGET") -> ON TRACK
